gram_tools/__init__.py
gram_tools/assets.py
gram_tools/crud.py
gram_tools/packer.py
gram_tools/visual.py
gram_tools/keyboards/__init__.py
gram_tools/keyboards/menu.py
gram_tools/keyboards/pagination.py
gram_tools-1.0.4.dist-info/LICENSE
gram_tools-1.0.4.dist-info/METADATA
gram_tools-1.0.4.dist-info/WHEEL
gram_tools-1.0.4.dist-info/top_level.txt
gram_tools-1.0.4.dist-info/RECORD
