Metadata-Version: 2.1
Name: gram_tools
Version: 1.0.4
Summary: Utilities for streamlined aiogram bot development.
Home-page: https://github.com/DedInc/gram-tools
Author: Maehdakvan
Author-email: visitanimation@google.com
Project-URL: Bug Tracker, https://github.com/DedInc/gram-tools/issues
Classifier: Programming Language :: Python :: 3
Classifier: License :: OSI Approved :: MIT License
Classifier: Operating System :: OS Independent
Requires-Python: >=3.6
License-File: LICENSE
Requires-Dist: aiogram>=3.0.0
Requires-Dist: orjson
Requires-Dist: aiofiles
Requires-Dist: numpy
Requires-Dist: networkx
Requires-Dist: matplotlib
